hysterical_ticket/__init__.py
hysterical_ticket/ui.py
hysterical_ticket/component/__init__.py
hysterical_ticket/component/collector.py
hysterical_ticket/component/fns.py
hysterical_ticket/component/prompts.py
hysterical_ticket/component/verifier.py
hysterical_ticket-0.2.1.dist-info/METADATA
hysterical_ticket-0.2.1.dist-info/WHEEL
hysterical_ticket-0.2.1.dist-info/top_level.txt
hysterical_ticket-0.2.1.dist-info/RECORD
